simple_site_crawler/__init__.py
simple_site_crawler/command_line.py
simple_site_crawler/site_crawler.py
simple_site_crawler/utils.py
simple_site_crawler/webpage.py
simple_site_crawler/test/test_command_line.py
simple_site_crawler/test/test_site_crawler.py
simple_site_crawler/test/test_utils.py
simple_site_crawler/test/test_webpage.py
simple_site_crawler/test/files/example.html
simple_site_crawler/test/files/sitemap.xml
simple_site_crawler-0.1.1.data/scripts/simple-site-crawler
simple_site_crawler-0.1.1.dist-info/DESCRIPTION.rst
simple_site_crawler-0.1.1.dist-info/METADATA
simple_site_crawler-0.1.1.dist-info/RECORD
simple_site_crawler-0.1.1.dist-info/WHEEL
simple_site_crawler-0.1.1.dist-info/metadata.json
simple_site_crawler-0.1.1.dist-info/top_level.txt
