Metadata-Version: 2.0
Name: simple-site-crawler
Version: 0.1.1
Summary: Simple website crawler that asynchronously crawls a website and all subpages that it can find, along with static content that they rely on.
Home-page: https://github.com/pawelad/simple-site-crawler
Author: Paweł Adamczak
Author-email: pawel.ad@gmail.com
License: MIT License
Download-URL: https://github.com/pawelad/simple-site-crawler/releases/latest
Keywords: website crawler sitemap
Platform: UNKNOWN
Classifier: Development Status :: 4 - Beta
Classifier: Environment :: Console
Classifier: Intended Audience :: End Users/Desktop
Classifier: License :: OSI Approved :: MIT License
Classifier: Operating System :: OS Independent
Classifier: Programming Language :: Python
Classifier: Programming Language :: Python :: 3
Classifier: Programming Language :: Python :: 3.5
Classifier: Programming Language :: Python :: 3.6
Classifier: Topic :: Utilities
Requires-Dist: aiodns (>=1.1.1)
Requires-Dist: aiohttp (>=1.2.0)
Requires-Dist: beautifulsoup4 (>=4.5.3)
Requires-Dist: cchardet (>=1.1.2)
Requires-Dist: click (>=6.7)
Requires-Dist: html5lib (>=1.0b10)
Provides-Extra: testing
Requires-Dist: pytest; extra == 'testing'
